Workbook

Sheet Progress Table
A1: Problem Statement | B1: Objectives | C1: Scopes | D1: Features | E1: Target Date of Completion | F1: Date of Completion | G1: Remarks | I1: Detailed | J1: May 9 Notes | K1: May 23 Notes | L1: Comments
A2: How to elevate the way Makaton is integrated and utilized in learning instruction that will effectively support teacher-guided Makaton instruction critical for special needs of learners with communicative impediments? | B2: To elevate the way Makaton is integrated and utilized in learning instruction by designing and developing a web-based multimodal machine learning-based Makaton learning support system that will effectively support teacher-guided Makaton instruction critical for special needs of learners with communicative impediments. | C2: Implementation of Overall MakaLearn System - Account Management Module - Makaton Learning Content Management Module - Interactive Makaton Symbol Playground and Activity Module - Makaton Hand Gesture Recognition and LLM-Based Corrective Feedback Module | D2: OVERALL MAKALEARN SYSTEM | E2: September 23, 2026
D3: - Teacher and Administrator Account and Profile Management | E3: August 26, 2026 | I3: Ayaw na meron na sscroll, paliitin yung stuff | K3: OK
D4: - Teacher Account Management and Admin Content Oversight | E4: August 27, 2026 | H4: OK | I4: dapat yung button directed sa pag add ng exercise pag walang current exercise | J4: OK
D5: - Makaton Multimedia Learning Content and Symbol Card Management | E5: August 29, 2026 | I5: ayusin connection | J5: kailangan and dapat parang specific dapat personalize based sa information ng user | K5: di ok
D6: - Makaton Content Category and Lesson Management | E6: August 31, 2026 | I6: wag total ng whole life time per day lang ipakita sa dashboard | J6: computation ng kilo calories (hanap ng pang justify) | K6: ok
D7: - Activity Creation, Drafting, Library, and Player | E7: September 3, 2026 | I7: yung important stuff na dapat nakikita daily dapat nakikita agad | J7: connect pa yung data | K7: ok
D8: - Interactive Makaton Symbol Learning and Audio Playback | E8: September 7, 2026
D9: - MSAV-Based Symbol Arrangement Validation | E9: September 8, 2026
D10: - Makaton Hand Gesture Recognition Model Development | E10: September 14, 2026 | J10: 3 lang per scroll sa dashboard | K10: ok
D11: - Camera-Based Makaton Gesture Practice, Recognition, and Feedback Display | E11: September 18, 2026 | J11: OK
D12: - LLM-Based Corrective Feedback | E12: September 20, 2026 | I12: need makita | K12: ok
B13: To design, develop, and evaluate a web-based interactive multimodal Makaton symbol learning module integrated with the Makaton Symbol Arrangement and Validation Algorithm that will help enable repeated Makaton symbol association, arrangement validation, and reinforcement among SPED learners. | C13: Implementation of Interactive Makaton Symbol Playground and Activity Module - Symbol Exploration Playground - Interactive Symbol Activities - Symbol Audio Playback - MSAV Algorithm Integration | D13: INTERACTIVE MAKATON SYMBOL PLAYGROUND AND ACTIVITY MODULE | E13: September 8, 2026
D14: Activity Creation and Drafting | E14: September 2, 2026 | H14: OK
D15: - Create manual activities | E15: September 1, 2026 | H15: OK
D16: - Generate activity drafts from learning items | E16: September 2, 2026 | I16: wag gawin week the whole year, 1-4th week of the month (5 if possible) | J16: year (most active in date // gawin buo | K16: ok
D17: - Create shared or private visibility option | E17: September 2, 2026 | H17: OK
D18: - Save activity records | E18: September 2, 2026 | H18: OK
D19: Activity Library and Player | E19: September 3, 2026
D20: - Create and view available activities | E20: September 3, 2026 | I20: need makita | J20: per week update ng bmi plus pic ng progress | K20: di ok
D21: - Create activity player | E21: September 3, 2026 | J21: OK
D22: - Create answer activity questions | E22: September 3, 2026
D23: - View final score | E23: September 3, 2026 | J23: i move yung health metrics sa progress trackin | K23: ok
D24: Makaton Symbol Exploration Playground | E24: September 4, 2026
D25: - View available Makaton/PECS symbol cards | E25: September 4, 2026 | H25: OK
D26: - Filter symbol cards by category | E26: September 4, 2026 | H26: OK
D27: - Select symbol cards to communicate | E27: September 4, 2026 | I27: disable pag modify sa past | J27: di pa pwede | K27: ok
D28: - Arrange selected symbol cards | E28: September 4, 2026 | H28: OK
D29: - Clear selected symbol cards | E29: September 4, 2026 | H29: OK
D30: MSAV Symbol Arrangement Validation | E30: September 8, 2026 | H30: OK
D31: - Validate symbol arrangements using rule-based logic | E31: September 8, 2026 | H31: OK
D32: - Display correct or incorrect feedback | E32: September 8, 2026 | H32: OK
D33: Drag-and-Drop Activity | E33: September 5, 2026 | H33: OK
D34: - Drag symbol cards to answers | E34: September 5, 2026 | H34: OK
D35: - Drop symbol cards into target areas | E35: September 5, 2026 | H35: OK
D36: - Check dropped answers | E36: September 5, 2026 | H36: OK
D37: - Show correct or incorrect feedback | E37: September 5, 2026
D38: - Display activity score | E38: September 5, 2026 | H38: OK
D39: Matching-Type Activity | E39: September 6, 2026 | H39: OK
D40: - Match words to symbol cards | E40: September 6, 2026
D41: - Check matched answers | E41: September 6, 2026 | H41: OK
D42: - Show correct or incorrect feedback | E42: September 6, 2026 | H42: OK
D43: - Display activity score | E43: September 6, 2026
D44: Fill-in-the-Blank Activity | E44: September 7, 2026 | H44: OK
D45: - Select the missing word or symbol | E45: September 7, 2026 | H45: OK
D46: - Complete symbol-based sentence prompts | E46: September 7, 2026
D47: - Check fill-in-the-blank answers | E47: September 7, 2026
D48: - Show correct or incorrect feedback | E48: September 7, 2026
D49: - Display activity score | E49: September 7, 2026
D50: Makaton Symbol Audio Playback | E50: September 7, 2026
D51: - Play audio for selected Makaton/PECS cards | E51: September 7, 2026
D52: - Play audio in activities | E52: September 7, 2026
D53: - Play assembled sentence audio | E53: September 7, 2026
B54: To develop and evaluate an optimized computer vision-based Makaton hand gesture recognition model integrated with generative AI-based corrective feedback that will improve Makaton hand gesture practice. | C54: Implementation of Makaton Gesture Recognition and LLM-Based Corrective Feedback Module - Camera-Based Makaton Hand Gesture Practice - Makaton Hand Gesture Recognition Model Integration - LLM-Based Corrective Feedback | D54: MAKATON GESTURE RECOGNITION AND LLM-BASED CORRECTIVE FEEDBACK MODULE | E54: September 20, 2026
D55: Makaton Hand Gesture Recognition Model Development | E55: September 14, 2026
D56: - Record and validate hand gesture samples | E56: September 9, 2026
D57: - Extract and prepare the hand landmark dataset | E57: September 10, 2026
D58: - Develop and train baseline and optimized models | E58: September 12, 2026
D59: - Evaluate and compare model performance and training behavior | E59: September 13, 2026
D60: - Select the best-performing model for system integration | E60: September 14, 2026
D61: Camera-Based Gesture Display | E61: September 15, 2026
D62: - Create open webcam preview | E62: September 15, 2026
D63: - Show live camera frame | E63: September 15, 2026
D64: - Display hand landmark overlay | E64: September 15, 2026
D65: - Stop camera preview | E65: September 15, 2026
D66: Makaton Gesture Reference Panel | E66: September 16, 2026
... D87: - Display teacher next-step guidance | E87: September 20, 2026
B88: To design, develop, and evaluate a tailored web-based learning facility and content management platform for SPED teachers that will assist in managing and delivering organized and structured Makaton learning instruction. | C88: Implementation of Account Management Module - Login for Teachers and Admins - Account Settings and Profile Management - Teacher Account Management - Admin Content Oversight Implementation of Makaton Learning Content Management Module - Multimedia Content for Demonstration of Makaton Symbols, Gestures, and Speech - Makaton Symbol Card Repository - Upload and Edit of Makaton Symbol Cards - Makaton Content Category Filter - Lesson Management | D88: ACCOUNT MANAGEMENT AND MAKATON LEARNING CONTENT MANAGEMENT MODULES | E88: August 31, 2026
D89: Login for Teachers and Admins | E89: August 25, 2026
D90: - Login with teacher account | E90: August 25, 2026
D91: - Login with administrator account | E91: August 25, 2026
D92: - Redirect users by role | E92: August 25, 2026
D93: - Apply security for authenticated routes | E93: August 25, 2026
D94: Account Settings and Profile Management | E94: August 26, 2026
D95: - View profile settings | E95: August 26, 2026
D96: - Update profile details | E96: August 26, 2026
D97: - Manage password section | E97: August 26, 2026
D98: - Manage accessibility settings | E98: August 26, 2026
D99: Teacher Account Management | E99: August 27, 2026
D100: - View teacher accounts | E100: August 27, 2026
... D136: - Open related activity or practice action | E136: August 31, 2026
A140: Prepared By:
A144: Lugue, Julian Matthew O. | B144: Oñate, James Gabrielle G. | C144: Perez, Lloyd Raphael M.
A149: Approved By:
A153: Dennis A. Martillano

Sheet Copy of Progress
A2: Overview of feature readiness per module
B4: Total Features | C4: Done (OK) | D4: Pending | E4: Overall %
B5: =C22 -> 70 | C5: =D22 -> #REF! | D5: =B5-C5 -> #REF! | E5: =E22 -> #REF!
A7: # | B7: Module | C7: Total Features | D7: Done (OK) | E7: % Complete | F7: Status | G7: Notes
A8: 1 | B8: Dashboard | C8: 5 | D8: =COUNTIF('Progress Table'!F3:F7, "OK" ) -> 0 | E8: =D8/C8 -> 0 | F8: In Progress | G8: Quick-launch OK; others pending or removed
A9: 2 | B9: Achievement & Leaderboard | C9: 5 | D9: 5 | E9: =D9/C9 -> 1 | F9: Not Started | G9: Pop-up, combine badges — all pending
A10: 3 | B10: Progress Tracking | C10: 8 | D10: 8 | E10: =D10/C10 -> 1 | F10: In Progress | G10: Body Metrics sub-features pending
A11: 4 | B11: Training Program | C11: 7 | D11: 7 | E11: =D11/C11 -> 1 | F11: In Progress | G11: Add/start restrictions need fixing
A12: 5 | B12: Exercise Library | C12: 3 | D12: =COUNTIF(#REF!, "OK" ) -> #REF! | E12: =D12/C12 -> #REF! | F12: In Progress | G12: Images/GIFs for some exercises missing
A13: 6 | B13: Exercise Session | C13: 11 | D13: =COUNTIF('Progress Table'!F30:F34, "OK" ) -> 0 | E13: =D13/C13 -> 0 | F13: Complete | G13: All sub-modes complete
A14: 7 | B14: Post-Exercise Summary | C14: 3 | D14: =COUNTIF(#REF!, "OK" ) -> #REF! | E14: =D14/C14 -> #REF! | F14: Not Started | G14: Wording, photo limit, route — all pending
A15: 8 | B15: Fitness AI Chatbot | C15: 5 | D15: 4 | E15: =D15/C15 -> 0.8 | F15: Not Started | G15: All features pending
A16: 9 | B16: User Customization | C16: 9 | D16: 6 | E16: =D16/C16 -> 0.66666667 | F16: In Progress | G16: Only Settings (notif + logout) done
A17: 10 | B17: Social — Feed | C17: 2 | D17: =COUNTIF(#REF!, "OK" ) -> #REF! | E17: =D17/C17 -> #REF! | F17: Not Started | G17: Both features pending
A18: 11 | B18: Social — Groups | C18: 5 | D18: =COUNTIF('Progress Table'!F35:F36, "OK" ) -> 0 | E18: =D18/C18 -> 0 | F18: Complete | G18: All complete
A19: 12 | B19: Social — Community Leaderboard | C19: 2 | D19: =COUNTIF('Progress Table'!F37:F39, "OK" ) -> 0 | E19: =D19/C19 -> 0 | F19: Complete | G19: All complete
A20: 13 | B20: Social — Messages | C20: 2 | D20: =COUNTIF('Progress Table'!F40:F42, "OK" ) -> 0 | E20: =D20/C20 -> 0 | F20: Complete | G20: All complete
A21: 14 | B21: Social — Profile | C21: 3 | D21: =COUNTIF('Progress Table'!F43:F45, "OK" ) -> 0 | E21: =D21/C21 -> 0 | F21: Complete | G21: All complete
A22: TOTAL | C22: =SUM(C8:C21) -> 70 | D22: =SUM(D8:D21) -> #REF! | E22: =AVERAGE(E8:E21) -> #REF!

Sheet Progress
A1: Feature Completion Tracker
A2: Overview of feature readiness per module
C4: Total Features | D4: Done (OK) | E4: Pending | F4: Overall %
C5: =E22 -> 0 | D5: =F22 -> #REF! | E5: =C5-D5 -> #REF! | F5: =G22 -> #DIV/0!
A7: # | B7: Objectives | C7: Scope | D7: Module | E7: Total Features | F7: Done (OK) | G7: % Complete | H7: Status | I7: Notes
A8: 1 | B8: Main Objective | F8: =COUNTIF('Progress Table'!F3:F7, "OK" ) -> 0 | G8: =F8/E8 -> #DIV/0! | H8: =_xludf.IFS(G8=1, "Complete", G8>0, "In Progress", G8=0, "Not Started") -> #NAME?
A9: 2 | F9: =COUNTIF('Progress Table'!F10:F12, "OK" ) -> 0 | G9: =F9/E9 -> #DIV/0! | H9: =_xludf.IFS(G9=1, "Complete", G9>0, "In Progress", G9=0, "Not Started") -> #NAME?
A10: 3 | B10: Objective 1 | F10: =COUNTIF('Progress Table'!F14:F23, "OK" ) -> 0 | G10: =F10/E10 -> #DIV/0! | H10: =_xludf.IFS(G10=1, "Complete", G10>0, "In Progress", G10=0, "Not Started") -> #NAME? | I10: All complete
A11: 4 | B11: Objective 2 | F11: =COUNTIF('Progress Table'!F25:F29, "OK" ) -> 0 | G11: =F11/E11 -> #DIV/0! | H11: =_xludf.IFS(G11=1, "Complete", G11>0, "In Progress", G11=0, "Not Started") -> #NAME? | I11: All complete
A12: 5 | F12: =COUNTIF(#REF!, "OK" ) -> #REF! | G12: =F12/E12 -> #REF! | H12: =_xludf.IFS(G12=1, "Complete", G12>0, "In Progress", G12=0, "Not Started") -> #NAME? | I12: All complete
A13: 6 | F13: =COUNTIF('Progress Table'!F30:F34, "OK" ) -> 0 | G13: =F13/E13 -> #DIV/0! | H13: =_xludf.IFS(G13=1, "Complete", G13>0, "In Progress", G13=0, "Not Started") -> #NAME? | I13: All complete
A14: 7 | F14: =COUNTIF(#REF!, "OK" ) -> #REF! | G14: =F14/E14 -> #REF! | H14: =_xludf.IFS(G14=1, "Complete", G14>0, "In Progress", G14=0, "Not Started") -> #NAME? | K14: Objective Completion Tracker
A15: 8 | F15: =COUNTIF(#REF!, "OK" ) -> #REF! | G15: =F15/E15 -> #REF! | H15: =_xludf.IFS(G15=1, "Complete", G15>0, "In Progress", G15=0, "Not Started") -> #NAME? | K15: Overview of feature readiness per module
A16: 9 | F16: =COUNTIF(#REF!, "OK" ) -> #REF! | G16: =F16/E16 -> #REF! | H16: =_xludf.IFS(G16=1, "Complete", G16>0, "In Progress", G16=0, "Not Started") -> #NAME?
A17: 10 | B17: Objective 3 | F17: =COUNTIF(#REF!, "OK" ) -> #REF! | G17: =F17/E17 -> #REF! | H17: =_xludf.IFS(G17=1, "Complete", G17>0, "In Progress", G17=0, "Not Started") -> #NAME? | I17: All complete | L17: Total Objective | M17: Done (OK) | N17: Pending | O17: Overall %
A18: 11 | F18: =COUNTIF('Progress Table'!F35:F36, "OK" ) -> 0 | G18: =F18/E18 -> #DIV/0! | H18: =_xludf.IFS(G18=1, "Complete", G18>0, "In Progress", G18=0, "Not Started") -> #NAME? | I18: All complete | L18: 4 | M18: 0 | N18: =L18-M18 -> 4 | O18: =O25 -> #DIV/0!
A19: 12 | F19: =COUNTIF('Progress Table'!F37:F39, "OK" ) -> 0 | G19: =F19/E19 -> #DIV/0! | H19: =_xludf.IFS(G19=1, "Complete", G19>0, "In Progress", G19=0, "Not Started") -> #NAME? | I19: All complete
A20: 13 | F20: =COUNTIF('Progress Table'!F40:F42, "OK" ) -> 0 | G20: =F20/E20 -> #DIV/0! | H20: =_xludf.IFS(G20=1, "Complete", G20>0, "In Progress", G20=0, "Not Started") -> #NAME? | I20: All complete | K20: # | L20: Objectives | M20: Total Scope | N20: Done (OK) | O20: % Complete | P20: Status | Q20: Notes
A21: 14 | F21: =COUNTIF('Progress Table'!F43:F45, "OK" ) -> 0 | G21: =F21/E21 -> #DIV/0! | H21: =_xludf.IFS(G21=1, "Complete", G21>0, "In Progress", G21=0, "Not Started") -> #NAME? | I21: All complete | K21: 1 | L21: Main Objective | N21: =COUNTIF('Progress Table'!F26:F29, "OK" ) -> 0 | O21: =N21/M21 -> #DIV/0! | P21: =_xludf.IFS(O21=1, "Complete", O21>0, "In Progress", O21=0, "Not Started") -> #NAME?
A22: TOTAL | E22: =SUM(E8:E21) -> 0 | F22: =SUM(F8:F21) -> #REF! | G22: =AVERAGE(G8:G21) -> #DIV/0! | K22: 2 | L22: Objective 1 | N22: =COUNTIF(#REF!, "OK" ) -> #REF! | O22: =N22/M22 -> #REF! | P22: =_xludf.IFS(O22=1, "Complete", O22>0, "In Progress", O22=0, "Not Started") -> #NAME?
K23: 3 | L23: Objective 2 | N23: =COUNTIF('Progress Table'!F30, "OK" ) -> 0 | O23: =N23/M23 -> #DIV/0! | P23: =_xludf.IFS(O23=1, "Complete", O23>0, "In Progress", O23=0, "Not Started") -> #NAME?
K24: 4 | L24: Objective 3 | N24: =COUNTIF('Progress Table'!F32:F34, "OK" ) -> 0 | O24: =N24/M24 -> #DIV/0! | P24: =_xludf.IFS(O24=1, "Complete", O24>0, "In Progress", O24=0, "Not Started") -> #NAME?
K25: TOTAL | M25: =SUM(M21:M24) -> 0 | N25: =SUM(N21:N24) -> #REF! | O25: =AVERAGE(O21:O24) -> #DIV/0!
K27: Scope Completion Tracker
K28: Overview of feature readiness per module
L30: Total Scopes | M30: Done (OK) | N30: Pending | O30: Overall %
L31: =COUNTIF(L34:L40, "<>") -> 7 | M31: 0 | N31: =L31-M31 -> 7 | O31: =O41 -> #REF!
K33: # | L33: Scopes | M33: Total Scope | N33: Done (OK) | O33: % Complete | P33: Status | Q33: Notes
K34: 1 | L34: Training Program | N34: =COUNTIF(#REF!, "OK" ) -> #REF! | O34: =N34/M34 -> #REF! | P34: =_xludf.IFS(O34=1, "Complete", O34>0, "In Progress", O34=0, "Not Started") -> #NAME?
K35: 2 | L35: Fitness AI Chatbot
K36: 3 | L36: Progress Tracking
K37: 4 | L37: Dashboard
K38: 5 | L38: User Customization | N38: =COUNTIF('Progress Table'!F30:F33, "OK" ) -> 0 | O38: =N38/M38 -> #DIV/0! | P38: =_xludf.IFS(O38=1, "Complete", O38>0, "In Progress", O38=0, "Not Started") -> #NAME?
K39: 6 | L39: Rewards and Leaderboard | N39: =COUNTIF(#REF!, "OK" ) -> #REF! | O39: =N39/M39 -> #REF! | P39: =_xludf.IFS(O39=1, "Complete", O39>0, "In Progress", O39=0, "Not Started") -> #NAME?
K40: 7 | L40: Group Fitness Challenge | N40: =COUNTIF(#REF!, "OK" ) -> #REF! | O40: =N40/M40 -> #REF! | P40: =_xludf.IFS(O40=1, "Complete", O40>0, "In Progress", O40=0, "Not Started") -> #NAME?
K41: TOTAL | M41: =SUM(M34:M40) -> 0 | N41: =SUM(N34:N40) -> #REF! | O41: =AVERAGE(O34:O40) -> #REF!

Sheet AI Response Comparison

Sheet Sample 1
A1: FITNESS BUDDY
A2: 1 | B2: Getting Started | C2: Create your account, log in, and set up your profile
A3: 2 | B3: The Dashboard | C3: Understand your home screen, BMI card, progress ring, and menu
A4: 3 | B4: Training Program | C4: Build your weekly workout plan and browse the exercise library
A5: 4 | B5: Starting a Workout | C5: Launch a live session, track reps/time, and use the GPS map
A6: 5 | B6: After Your Workout | C6: Save your session stats and attach progress photos
A7: 6 | B7: Progress & Analytics | C7: Read your charts, switch metrics, and view fitness trends
A8: 7 | B8: AI Fitness Chatbot | C8: Ask the AI for advice, get personalised cardio guidance
A9: 8 | B9: Social & Community | C9: Join the Feed, create Groups, and climb the Leaderboard
A10: 9 | B10: Rewards & Achievements | C10: Unlock badges, spend coins in the shop, and customise avatar
A11: 10 | B11: Profile & Settings | C11: Edit your profile, manage notifications, and privacy options
A12: 01 · Getting Started
A13: # | B13: What to do | C13: Tap / Press this | D13: What you will see | E13: Tip / Note
A14: FIRST LAUNCH
A15: 1 | B15: Open the app | C15: Tap the Fitness Buddy icon on your home screen | D15: The splash screen with the Fitness Buddy logo. If you have logged in before, you will be sent straight to the Dashboard after 1.5 seconds. | E15: If you see the Dashboard immediately, your session is still active — no need to log in again.
A16: 2 | B16: Start the sign-up process | C16: Tap the 'Get Started' button | D16: The Login screen opens with fields for email and password.
A17: NEW USER — CREATE AN ACCOUNT
A18: 3 | B18: Go to the Sign Up screen | C18: Tap 'Sign Up' at the bottom of the Login screen | D18: The Sign Up screen with an Email field and a Password field.
A19: 4 | B19: Enter your email | C19: Tap the Email field and type your email address | D19: Your email appears in the field. | E19: Use a valid email — you will need it to reset your password later.
A20: 5 | B20: Enter a password | C20: Tap the Password field and type a password | D20: Password is hidden behind dots. | E20: Firebase requires a minimum of 6 characters. Use a mix of letters and numbers.
A21: 6 | B21: Create your account | C21: Tap the 'Sign Up' button | D21: Account is created and the app moves to the Setup Profile wizard. | E21: If you see a red error toast, the email may already be in use — try a different one.
A22: RETURNING USER — LOG IN
A23: 3* | B23: Log in to your account | C23: Enter your email and password, then tap 'Login' | D23: If correct, you are taken directly to the Dashboard. If incorrect, a Toast error message appears. | E23: Tap 'Reset Password' in Settings if you have forgotten your password.
A24: SETUP PROFILE WIZARD (5 pages — tap Continue to advance)
A25: 7 | B25: Page 1 — Personal Info | C25: Fill in: Full Name, Username (@handle), Bio (optional). Tap 'Continue' | D25: Progress bar advances to 20%. Page 2 slides in. | E25: Your username will appear on the Leaderboard and Community Feed.
A26: 8 | B26: Page 2 — Body Metrics | C26: Fill in: Age, Weight (kg), Height (cm), Target Weight (kg). Tap 'Continue' | D26: Progress bar moves to 40%. Page 3 slides in. | E26: These values are used to calculate your BMI and calorie estimates.
A27: 9 | B27: Page 3 — Fitness Goals | C27: Fill in: Daily Step Goal, Daily Calorie Goal, Active Minutes Goal. Tap 'Continue' | D27: Progress bar moves to 60%. Page 4 slides in. | E27: A good starting step goal is 8,000 steps per day for beginners.
A28: 10 | B28: Page 4 — Workout Days | C28: Tap the day chips to select days (Mon–Sun). Tap 'Continue' | D28: Selected day chips highlight. Progress bar moves to 80%. | E28: These days are highlighted on your Training Program calendar.
A29: 11 | B29: Page 5 — Activity Level | C29: Tap the Activity Level spinner, choose a level, tap 'Finish & Start' | D29: Button briefly shows 'Saving…' then takes you to the Dashboard. | E29: Be honest — this helps the AI Chatbot give you accurate cardio guidance.
A31: 02 · The Dashboard
A32: # | B32: What to do | C32: Tap / Press this | D32: What you will see | E32: Tip / Note
A33: READING YOUR DASHBOARD
A34: 1 | B34: Open the Dashboard | C34: Tap the Home icon (house) in the bottom navigation bar | D34: The main Dashboard screen with your name, BMI card, and activity ring. | E34: The Dashboard updates in real time — data refreshes every time Firebase sends new information.
A35: 2 | B35: Check your BMI status | C35: Look at the BMI card at the top of the screen | D35: Your BMI number and a status label (e.g. 'Healthy', 'Overweight'). | E35: BMI is calculated from the weight and height you entered during setup.
A36: 3 | B36: Check your daily progress | C36: Look at the circular activity ring and horizontal progress bar | D36: A percentage and text showing steps to next milestone. | E36: When you reach your step goal, the ring fills completely and shows 'Milestone reached! 🏆'.
A37: 4 | B37: View recent achievements | C37: Scroll down to the achievements list | D37: A horizontal list of up to 5 recent achievement badges you have earned. | E37: Tap an achievement to see full details in the Achievements screen.
A38: NAVIGATING THE APP
A39: 5 | B39: Use the bottom navigation bar | C39: Tap any of the 5 icons: Dumbbell · Robot · House · Chart · People | D39: The selected screen opens. The tapped icon turns the primary brand colour. | E39: The nav bar stays visible on every main screen.
A40: 6 | B40: Open the side menu | C40: Tap the hamburger icon (≡) in the top-right of the header bar | D40: A popup menu: Edit Profile · Settings · Logout. | E40: Edit Profile' opens Health Metrics in edit mode.
A41: 7 | B41: Edit your health data | C41: Tap 'Edit Profile' in the side menu | D41: The Health Metrics screen opens pre-filled. Update and tap 'Update Data'. | E41: Update your weight regularly — keeps your BMI and calorie estimates accurate.
A42: 8 | B42: Log out | C42: Tap the hamburger menu (≡) → tap 'Logout' | D42: You are signed out and returned to the Login screen. | E42: Your data is saved in Firebase — logging out does not delete anything.
A44: 03 · Training Program
A45: # | B45: What to do | C45: Tap / Press this | D45: What you will see | E45: Tip / Note
A46: OPENING THE TRAINING PROGRAM
A47: 1 | B47: Open Training Program | C47: Tap the Dumbbell icon in the bottom navigation bar | D47: The Training Program screen with a date header and a horizontal calendar.
A48: USING THE CALENDAR
A49: 2 | B49: Navigate the week calendar | C49: Swipe left or right on the calendar row | D49: The calendar snaps in 7-day week blocks spanning 2 years (104 weeks total). | E49: The calendar jumps to the nearest Sunday boundary — this is intentional.
A50: 3 | B50: Select a specific day | C50: Tap any day tile in the calendar row | D50: The selected day tile highlights. The exercise list updates for that day. | E50: Tap today's date to return to the current day's schedule.
A51: ADDING EXERCISES TO YOUR PLAN
A52: 4 | B52: Add an exercise to a date | C52: Select the target date, then tap the blue '+' floating action button | D52: The Exercise Library opens in Selection Mode. | E52: The selected date is passed to the Library — exercises you pick will be assigned to that day.
A53: 5 | B53: Choose an exercise from the Library | C53: Tap any exercise card in the Library | D53: The Exercise Description screen opens showing name, category, intensity, equipment, and demo image.
A54: 6 | B54: Add the exercise to your plan | C54: Tap 'Add to Calendar' on the Exercise Description screen | D54: You are returned to Training Program. The exercise now appears for the selected date. | E54: You can add as many exercises as you like to one day.
A55: 7 | B55: Delete an exercise from the plan | C55: Swipe the exercise row to the left | D55: A delete action is revealed. The row is removed and deleted from Firebase. | E55: This only removes the exercise from that date — it does not delete it from the Library.
A56: BROWSING THE EXERCISE LIBRARY
A57: 8 | B57: Browse all exercises | C57: Tap the 'Exercise Library' button | D57: The full Exercise Library opens in Browse Mode with all cardio exercises. | E57: In Browse Mode, tapping an exercise opens its details — no exercise will be added to your plan.
A58: 9 | B58: Search for an exercise | C58: Tap the search bar and type a keyword (e.g. 'jump rope', 'cycling') | D58: The list filters in real time to show only matching exercises. | E58: You can search by exercise name or category name.
A59: 10 | B59: Filter by category or intensity | C59: Tap the Filter icon → select chips → tap 'Apply' | D59: The exercise list updates to show only matching exercises. | E59: Tap 'Reset' in the filter sheet to clear all filters.
A60: 11 | B60: Read an exercise description | C60: Tap any exercise card | D60: Exercise Description screen shows: Name, category, intensity badge, equipment, tracking type, demo image. | E60: Tracking Type' tells you how the live session will log this exercise.
A62: 04 · Starting a Workout
A63: # | B63: What to do | C63: Tap / Press this | D63: What you will see | E63: Tip / Note
A64: STARTING A SESSION
A65: 1 | B65: Launch a workout from your plan | C65: In Training Program, tap an exercise → tap 'Start Exercise' | D65: The Live Exercise Session screen opens with two tabs: Stats and a dynamic tool tab. | E65: The tab label changes based on the exercise type set in the Library.
A66: TAB 1 — STATS (always visible)
A67: 2 | B67: Monitor your live stats | C67: Keep 'Stats' tab selected (default) | D67: Four live counters: Steps · Timer · Distance · Calories. | E67: The step counter uses your phone's built-in sensor. Keep the phone in your pocket or hand.
A68: 3 | B68: Start / pause the timer | C68: Tap the Start button in the Stats area | D68: Timer begins counting up. Tap again to pause. | E68: Steps are counted whether the timer is running or not.
A69: TAB 2 — DYNAMIC TOOL (changes by exercise type)
A70: 4 | B70: LOG SETS & REPS (Sets & Reps type) | C70: Tap the 'Log' tab → enter Weight and Reps → tap '+ Add Set' | D70: Each set is saved in a scrollable list showing set number, weight, and reps. | E70: You can log as many sets as needed. Sets are saved even if you navigate back to Stats.
A71: 5 | B71: TIMER COUNTDOWN (Duration Only type) | C71: Tap the 'Timer' tab → set target duration → tap 'Start Set' | D71: A large countdown timer runs. A notification sounds when it reaches zero. | E71: Tap 'Add Set' after each interval to log multiple timed sets.
A72: 6 | B72: GPS MAP ROUTE (GPS / Outdoor type) | C72: Tap the 'Map' tab → grant location permission → tap 'Start Recording' | D72: Your location appears on the map. A blue polyline traces your route in real time. | E72: Stay outside with a clear sky for the most accurate GPS signal.
A73: 7 | B73: SIMPLE COMPLETION CHECK (Simple Check type) | C73: Tap the 'Done' tab → tap the checkmark when finished | D73: A confirmation that the exercise has been marked complete. | E73: Used for stretching or warm-up routines where tracking numbers is not needed.
A74: FINISHING YOUR WORKOUT
A75: 8 | B75: End the session | C75: Tap 'Finish Workout' | D75: The app compiles all data and automatically opens the Post-Workout Summary screen. | E75: Do not close the app before tapping 'Finish Workout' — unsaved data will be lost.
A77: 05 · After Your Workout
A78: # | B78: What to do | C78: Tap / Press this | D78: What you will see | E78: Tip / Note
A79: REVIEWING YOUR RESULTS
A80: 1 | B80: View your session summary | C80: This screen opens automatically after you tap 'Finish Workout' | D80: A summary card: Exercise image or GPS map · Total Work · Average Level · Intensity · Active Time · Fastest Set. | E80: Stats depend on exercise type — GPS shows distance/pace; strength shows volume/intensity.
A81: 2 | B81: Understand each metric | C81: Read the summary cards on screen | D81: Total Work · Intensity · Active Time · Fastest Set — each defined on-screen. | E81: These metrics are calculated from the sets and times logged during the live session.
A82: ADDING PHOTOS
A83: 3 | B83: Attach a progress photo (optional) | C83: Tap the photo add button / camera icon in the photo section | D83: Your phone's photo picker opens. You can select up to 5 photos. | E83: Photos are compressed and saved alongside your workout data in Firebase.
A84: 4 | B84: Remove a photo before saving | C84: Tap the × button on any photo thumbnail | D84: The photo is removed from the selection list. | E84: You cannot add photos after saving — make your selection before tapping 'Save Workout'.
A85: SAVING OR DISCARDING
A86: 5 | B86: Save your workout | C86: Tap 'Save Workout' | D86: A saving indicator appears, then you return to the Dashboard. Your workout is stored in Exercise History. | E86: Saving also awards fitness points, which appear on the Leaderboard.
A87: 6 | B87: Discard the session | C87: Tap 'Discard' | D87: A confirmation dialog appears. Tap 'Discard' to confirm, or 'Cancel' to go back. | E87: Discarded sessions do not appear in history and do not award points.
A89: 06 · Progress & Analytics
A90: # | B90: What to do | C90: Tap / Press this | D90: What you will see | E90: Tip / Note
A91: OPENING PROGRESS TRACKING
A92: 1 | B92: Open Progress Tracking | C92: Tap the Chart icon in the bottom navigation bar | D92: The Progress Tracking screen with a line chart showing your Steps data for the current year.
A93: SWITCHING METRICS AND TIMEFRAMES
A94: 2 | B94: Change the metric displayed | C94: Tap one of the three metric buttons: Steps · Minutes · Calories | D94: The chart re-draws to show the selected metric. | E94: Minutes' shows total active minutes per day — a good measure of consistency.
A95: 3 | B95: Change the timeframe view | C95: Tap one of the three timeframe buttons: Daily · Weekly · Monthly | D95: The chart re-draws with the new grouping. X-axis labels update to match. | E95: Monthly view is best for spotting long-term trends.
A96: 4 | B96: Navigate between years | C96: Tap the '+' or '−' buttons next to the year label | D96: The chart shifts forward or backward one year. | E96: Your full workout history is stored — you can go back to the start of your activity.
A97: 5 | B97: Read a specific data point | C97: Tap any bar or point on the chart | D97: A popup label appears showing the exact value and date. | E97: Long-press on the chart to drag the selection across multiple data points.
A98: 6 | B98: Share your progress chart | C98: Tap the Share / Export button | D98: The chart is captured as an image and the Android share sheet opens. | E98: Great for sharing your consistency streak with friends or your coach.
A99: DETAILED FITNESS ANALYTICS
A100: 7 | B100: Open detailed analytics | C100: Tap the 'Fitness Progress' shortcut from Progress Tracking | D100: The Fitness Progress screen with tabs: GPS Map · Strength · Cardio.
A101: 8 | B101: Switch activity type view | C101: Tap the tabs: GPS Map · Strength · Cardio | D101: Stat cards, trend chart, and activity history list all update for the selected category.
A102: 9 | B102: Swipe through comparison cards | C102: Swipe left or right on the comparison card section | D102: Side-by-side cards comparing different exercises or time periods. | E102: Use these to identify which exercises you are improving at most.
A103: 10 | B103: View your exercise history | C103: Tap the Chart icon → tap 'Exercise History' | D103: A monthly calendar grid highlighting days when you exercised, and a scrollable list below. | E103: Tap '<' and '>' to navigate between months.
A105: 07 · AI Fitness Chatbot
A106: # | B106: What to do | C106: Tap / Press this | D106: What you will see | E106: Tip / Note
...

Sheet Sample 2
A1: How can a mobile health application be designed to provide a platform for Filipino non-gym-goers to overcome specific motivational barriers — lack of time, guidance, and training plan — that prevent them from adhering to a consistent cardiovascular exercise routine? | B1: [Main Objective] Design and develop an adaptive, AI-driven mobile platform for Filipino non-gym-goers that leverages gamified engagement to overcome motivational barriers and deliver personalized cardiovascular training to promote consistent adherence and mitigate NCD risks. | C1: Platform is focused exclusively on cardio-based exercises. Resistance training, strength-based plans, and sports-specific programs are NOT included. ML personalization is limited to user-provided inputs and in-app metrics only (no external wearable IoT sensor integration). | D1: Training Program Module • AI-Generated Adaptive Plans (adjust based on performance history & goals) • Exercise Library with multimedia content • Workout Timer / Session Tracker • Completion Tracking with visual progress milestones Fitness AI Chatbot Module • AI Recommendation Engine (custom suggestions from user data) • Motivational Messaging & adaptive reminders • Integration with Training Program module Progress Tracking Module • Daily, weekly, and monthly trend charts • Statistical summaries (calories burned, active time) • Goal Attainment Monitor Dashboard Module • Performance Overview with dynamic visualizations • Quick Access Shortcuts • Data-driven 'Bits and Tips' section User Customization Module • Profile Configuration (demographics, health metrics, fitness goals) • Notification, reminder, and privacy settings Rewards & Leaderboard Module • Achievement Badges + points/ranking system • Leaderboard Display for friendly competition Group Fitness Challenge Module • Friend System with Performance Comparison • Community Rankings • Team Challenges
B2: [Objective 1] Implement personalized goal-setting and progress visualization through an interactive cardio activity dashboard to enhance user motivation and engagement. | C2: Dashboard and progress features are driven by user-inputted personal stats (e.g., BMI). Gamification layer (rewards, leaderboards) is included to drive behavioral consistency. | D2: DASHBOARD (MODULE) • Personalized Goal-Setting Module • Intuitive Data Visualizations (progress charts, consistency tracking) • BMI-linked personalized goal display • WHO guideline-aligned progress indicators GAMIFICATION (MODULE) • Reward System (badges, points) • Competitive Leaderboards • Achievement-oriented experience design
B3: [Objective 2] Provide an Adaptive Training System to generate personalized workout activities and user support, tailored to the user's real-time schedule and activity goal. | C3: Machine learning model analyzes real-time progress, fatigue levels, and overall fitness status to auto-adjust intensity, duration, and type of workout. No human trainer required. | D3: ADAPTIVE TRAINING SYSTEM (MODULE) • ML Algorithm for dynamic cardio plan generation • Real-time adjustment of intensity, duration, and workout type • Fatigue & fitness level analysis AI CHATBOT (MODULE) • Flan-T5 fine-tuned LLM (domain: cardio & NCD) • RAG (Retrieval-Augmented Generation) Architecture • Keyword-based contextual search • Prompt Engineering layer • ROUGE-L evaluation (target F1-score ≥ 84%) • Negation Consistency Check (0% Polarity Violation Rate) • Out-of-domain query rejection (False Positive Rate control) • Gold Standard validation (3 categories: Psychoeducation, Risk Screening, Crisis Intervention)
B4: [Objective 3] Integrate social elements like Community Rankings to increase user engagement and retention through an interactive and supportive in-app community. | C4: Social ecosystem recreates gym-like accountability structures virtually. Supports peer-to-peer encouragement and collective goal-setting for non-gym-goers. | D4: SOCIAL / COMMUNITY (MODULE) • Friend System (connect with peers) • Workout Group Formation • Community Challenges (collaborative) • Community Rankings display • Team Challenge participation • Peer-to-peer encouragement mechanisms

Sheet Sample 3
A2: Get Started | E2: USER CUSTOMIZATION
A3: Signup | E3: Signup
A4: Login | E4: - Input of Email and Password
A5: CRUD Information | E5: Login
A6: Customize Avatar | E6: - Input of Email and Password
A7: Home/Dashboard | E7: - CRUD Personal Information
A8: Training | E8: -- Input of Age, Height, Weight, Target Weight, Target Steps, Minutes per Session, Availability Sched
A9: Calendar | E9: - Customize Avatar
A10: Generate AI Plan | B10: -- | E10: -- Allow user to customize their avatar
A11: Exercise | B11: Instructions (Video) | E11: DASHBOARD
A12: Finish Exercise | B12: Specify | E12: - Display Health metrics
A13: Progress Tracking | E13: -- BMI, Steps
A14: Home/Dashboard | E14: - Leaderboards (Friends)
E15: - Daily Bits n Tips
A16: Current Exercise | E16: - Performance Overview
A17: Chart | E17: - Current/Next Exercise
A18: Metrics | E18: TRAINING
A19: Chatbot | E19: - Calendar
E20: -- Day-to-day workout
A21: Home/Dashboard | B21: Friends Leaderboard | E21: - Exercise Library
A22: Bits n Tips | B22: Achievements | E22: -- List of all exercises
A23: Profile | E23: --- Video Instructions for each exercise
E24: - Start a new exercise
A25: Edit Profile | E25: - Selection of Exercise Type (GPS MAP, DURATION, VOLUME, TIMER REPS, MACHINE INPUT)
A26: Social
A27: Group Challenge | E27: Gps Map
E28: - Selection of Goal ( Step Count, Distance, Duration, Calories Burned, Freestyle)
E29: - Stats
E30: - Map (Location)
E32: Duration
E33: - Stats
E34: - Timer (per Set)
E36: Volume
E37: - Stats (Sets)
E39: Timer Reps
E40: - HIIT Configuration (AMRAP and Challenge)
E41: -- AMRAP (Sets, Work Time, Rest Time)
E42: -- Challenge (Sets, Work Time, Rest Time)
... E56: - Chat with AI

Sheet Sample 4
B2: Step by the Step
B3: Sign Up | E3: Sign Up
B4: Login | E4: - Username and Password
B5: Dashboard
B6: - Recent Activities | E6: Login
B7: - Bits n Tips | E7: - Username and Password
B8: - Achievements | E8: - User personal information for first time login
B9: - Daily Goal Tracking
B10: - Leaderboard | E10: Dashboard
B11: - Start New Activity | E11: - Recent activities (Recent workouts done and progress)
E12: - Achievements (Display badges, progress, recently achieved)
B13: Training Program | E13: - Leaderboard (Display Top Leaderboard or Current Leaderboard Ranking)
B14: - Daily Summary of Workout | E14: - Start New Activity (Redirects to starting another workout)
B15: - Workout Library
B16: AI Chatbot | E16: Training Program
B17: - User Input and Chatbot Response | E17: - Based on user information ai plan would be given; user can customize their own plan
B18: Progress Tracking | E18: - Day to day summary of what workouts are done and to be completed
B19: - Activity History | E19: - Workout Library (Display all available workout)
B20: - Performance History / Summary
B21: - Goal Attainment Monitor | E21: Progress Tracking
B22: Social | E22: - Activity History (Statistic about each activity done)
B23: - Friend System | E23: - Performance History (Weekly Monthly and Yearly)
B24: - User Feed | E24: - Goal Attainment (For users to see if they are still on track
B25: - Group Fitness Challenge
B26: - Friend Profile | E26: Social
E27: - Friend System (User can add one another)
E28: - User Feed (User can share, ask, interact about anything)
E29: - Group Fitness Challenge (Shared goal attainment within on circle)

Sheet Sample 5
A1: Problem Statement | B1: Objectives | C1: Scopes | D1: Features | E1: Remarks
A2: How can a mobile health application be designed to provide a platform for Filipino non-gym-goers to overcome the specific motivational barriers, such as lack of time, guidance, and training plan, that prevent them from adhering to a consistent cardiovascular exercise routine? | B2: Main Objective: Design and develop an adaptive, AI-driven mobile platform for Filipino non-gym-goers to overcome motivational barriers and deliver personalized cardio training. | C2: Implementation of Personalized Goal-Setting Structure for planning and monitoring fitness routines aligned with WHO guidelines. | D2: DASHBOARD (MODULE)
D3: - Workout Progress
D4: - Summary of Performance
D5: - Health Bits n Tips
D6: REWARDS & LEADERBOARD (MODULE)
D7: Display Achievements
D8: - Display Recent 5 Achievements
D9: - Display Achievement Title
D10: - Display Achievement Details
D11: - Display Date of Acquisition
D13: Display Leaderboard
D14: - Display Current Leaderboard Placement
B21: Objective 1: Implement personalized goal-setting and progress visualization through an interactive dashboard. | C21: Implementation of Progress Tracking Analyzing user metrics (like BMI) to generate impactful, accurate progress visualizations. | D21: PROGRESS TRACKING (MODULE)
D22: Display Trend Charts
D23: - Daily, Weekly and Monthly
B30: Objective 2: Provide an Adaptive Training System to generate personalized workout activities tailored to real-time schedules. | C30: Deployment of Machine Learning Algorithm A fully adaptive plan that adjusts intensity and duration based on fatigue and performance history. | D30: TRAINING PROGRAM (MODULE)
D31: - AI-Generated Adaptive Plans
D32: - Exercise Library (Multimedia)
D33: - Workout Timer & Session Tracker
B56: Objective 3: Provide real-time, context-based hints and guidance via an AI companion. | C56: Implementation of AI-Enabled Companion Powered by a curated knowledge base to deliver instant feedback and training advice. | D56: FITNESS AI CHATBOT (MODULE)
D57: AI Chatbot
D58: - AI Assistant (User Input, Chatbot Response)
D59: - Adaptive Reminders.
B64: Objective 4: Integrate social elements to increase engagement and retention through a supportive community. | C64: Implementation of Social Ecosystem Recreating gym dynamics via localized peer connections and collaborative challenges. | D64: GROUP FITNESS (MODULE)
D65: - Friend System & Performance Comparison
D66: - Community Rankings
D67: - Team Challenges.

Sheet Copy of For Checking
A1: User Customization
A2: Get Started
A3: SignUp | B3: SignUp (Email, Password)
B4: Next Step Button | C4: The Basics (Age, Height) Weight Goals (Weight, Target Weight) Step Goals (step sister) Schedule (Select Days, Minute per Session) Final Review (Remarks) | F4: Move "The Basics, Weight Goals..." to First-time Login
B5: Avatar Customization | C5: Customize Avatar Final Review
A6: SignIn | B6: Login (Username, Password)
B7: Login Button
A9: Login
A10: Home | B10: Dashboard | D10: Activity (Daily Goal Progress) Bits n Tips (Daily Bits n Tips) Achievement (List of achievements and Progresses) Leaderboard (Top 10) | E10: Three-line Menu | F10: Edit Profile (The Basics, Weight Goals, Step Goals, Schedule) Settings Logout
A11: Training | B11: Calendar | C11: Activities per Day
B12: AI Plan Button | C12: AI Generated Workout
B13: Library | C13: Search Filter Activities (Description)
B14: Add Workout | C14: Search Filter Activities (Description, Add to Calendar Button)
B15: Activities | C15: Description
C16: Start Exercise | D16: Stats (Distance, Etc.) Timer (Stopwatch, Set Buttons) Finish Exercise
A17: Chatbot | B17: Clear Conversation
B18: Chat Interface | C18: Chat Box (Type, Send) Chat History (User Prompts, Machine Feedback)
A19: Progress | B19: Charts (Daily, Weekly, Monthly)
B20: Statistical Summary of Metrics
B21: Goal Attainment Monitor
A25: Social & Group Fitness Challenge
A27: Avatar

Sheet Sheet1
A1: Problem Statement | B1: Objectives | C1: Scopes | D1: Features | E1: Features | F1: Remarks
A2: How can a mobile health application be designed to provide a platform for Filipino non-gym-goers to overcome the specific motivational barriers, such as lack of time, guidance, and training plan, that prevent them from adhering to a consistent cardiovascular exercise routine? | B2: Main Objective: The primary objective of this study is to design and develop an adaptive, AI-driven mobile platform for Filipino non-gym-goers, which leverages gamified engagement to overcome specific motivational barriers (lack of time, guidance, and planning) and deliver personalized cardiovascular training to promote consistent adherence and mitigate NCD risks. | C2: Implementation of Dashboard Implementation of Rewards and Leaderboard Implementation of User Customization | D2: Dashboard
D3: Fitness Data Management (BMI, calories burned, steps taken, active minutes) | E3: Display Current / Next Activity Progress in Dashboard
E4: Display Daily AI Generated Tips
D5: Leaderboard Data Management (Current placement, challenges won) | E5: Display Leaderboard in Dashboard
D6: Workout Data Management (Top exercises) | E6: Display Top Exercises in Dashboard
D7: Rewards and Leaderboard
D8: Achievement Badge System | E8: Achievement Unlocked
E9: View Achievements (All, Locked, Unlocked)
E10: View Achievement Details (Locked, Unlocked)
E11: Show Achievements in Dashboard (Recently Unlocked / Close to Unlocking)
E12: Show Unlocked Achievement in Social Feed
E13: Show Achievements in User Profile (Own Profile, Friends Profile)
E14: CRUD Achievements Displayed
E15: Show Achievement That Can be Unlocked From Particular Activity / Challenge
D16: Leaderboard System | E16: View Friend Leaderboard Through Dashboard (Allow Several Categories
E17: View Leaderboard in Group Fitness Challenge
D18: User Customization
D19: Avatar Customization | E19: View Current Avatar in Profile
E20: See Avatar in Dashboard
E21: Select / Update User Avatar
B22: Objective 1: Implement personalized goal-setting and progress visualization through an interactive cardio activity dashboard to enhance user motivation and engagement. | C22: Implementation of Progress Tracking Implementation of User Customization | D22: Progress Tracking
D23: Workout Logs / Activity Reports(Daily, weekly, monthly progress report) | E23: Progress Report Daily, Weekly, Monthly)
E24: Track Fitness Goal (Step Count, Exercise Time, etc)
E25: View Calculated BMI Status (Auto-updated based on weight inputs)
E26: See Fitness Goal Progress Bar in Dashboard
E27: See Activity History From Progress Report
E28: Show Completed Activities in Activity History
E29: Show Details of Completed Activities
D30: Export and Share Feature | E30: Share Progress Report to Feed or Outside Apps
D31: Data Visualization for Performance Trends | E31: Show Graphs and Charts for Progress Reports
E32: Show Graphs and Charts for Individual Activities / Challenges
D33: User Customization
D34: Account Management (Settings) | E34: CRUD Account Information (Username, Email, Password)
E35: Manage Notification Settings (Workout Reminders, Inactivity Alerts)
E36: Manage Privacy Settings (Profile Visibility)
E37: Logout / Deactivate Account
D38: Personal Fitness Information | E38: CRUD Health Metrics (Age, Height, Current Weight)
E39: CRUD Fitnness Goals (Target Weight, Descired Activity Level)
B40: Objective 2: Provide an Adaptive Training System to generate personalized workout activities and user support, tailored to the user's real-time schedule and activity goal. | C40: Implementation of Training Program Implementation of AI Chatbot | D40: Training Program
D41: Exercise Library (Instructional Videos) | E41: See Exercise Library Through Training Program
E42: See Selection of Exercises
E43: Filter Exercise Selection
E44: Search Through Exercise Selection
E45: Show Exercise Details (Description, Video, Calories, Time, Difficulty)
D46: Workout Calendar Scheduler | E46: See Calendar in Training Program
E47: See Different Workouts For Each Selected Date
E48: CRUD Workout Calendar
E49: Ask AI For Updated Workout Calendar
D50: Workout Tracker and Timer | E50: See in Exercises
E51: Timer (Start, Pause, Finish)
E52: Show Details in Timer (Steps, Distance, Pace, etc)
D53: AI-Generated Adaptive Workout Plan and Recommendations | E53: Generate Adaptive Workout
E54: Display Recommendations After Workout
D55: AI Chatbot
D56: Chat Interface | E56: Open / Close AI Chat Window
E57: Input Text Queries (Natural Language Questions)
E58: Display AI Generated Responses
E59: View Chat Session History
E60: Clear Chat History
D61: ML Chatbot Model | E61: Receive Content-Aware Responses (Tailored to user's track data/profile)
E62: Receive NCD-Specific Guidance
E63: Display Safety Warnings / Rejections (If query is medically unsafe or out of scope)
D64: Personalized Assistance | E64: Receive Motivational Responses
B65: Objective 3: Integrate social elements like Community Rankings to increase user engagement and retention through interactive and supportive in-app community. | C65: Implementation of Group Fitness Challenge | D65: Group Fitness Challenge
D66: Friend System | E66: Search for Users
E67: CRUD Friend Requests (Send, Accept, Reject, Cancel)
E68: View Friend List
E69: View Friend Profile (Achievements, Avatar, Basic Stats)
D70: Team Challenges | E70: View Available / Ongoing Group Challenges
E71: Create Join / Leave Group Challenge
E72: View Team Progress (Collective Steps, Distance, etc.)
E73: View Challenge Rules and Duration
E74: See Current Group Fitness Challenge on Dashboard
D75: Community Rankings | E75: View Community Leaderboard
E76: Filter Leaderboard Views (Group Fitness Challenge Only)
D77: Performance Comparison | E77: Stat Comparison with other Group
E78: View Personal Rank in Group Leaderboard

Sheet In Order
A1: Problem Statement | B1: Objectives | C1: Scopes | D1: Features | E1: Features | F1: Remarks
A2: How can a mobile health application be designed to provide a platform for Filipino non-gym-goers to overcome the specific motivational barriers, such as lack of time, guidance, and training plan, that prevent them from adhering to a consistent cardiovascular exercise routine? | B2: Main Objective: The primary objective of this study is to design and develop an adaptive, AI-driven mobile platform for Filipino non-gym-goers, which leverages gamified engagement to overcome specific motivational barriers (lack of time, guidance, and planning) and deliver personalized cardiovascular training to promote consistent adherence and mitigate NCD risks. | C2: Implementation of Dashboard Implementation of Rewards and Leaderboard Implementation of User Customization | D2: User Customization
D3: Account Management (Settings) | E3: Signup (Email, Password, The Basics, Weight Goals, Step Goals, Availability Schedule, Final Review) | F3: Move The Basics, Weight Goals, Step Goals, Availability Schedule, Final Review to First time Login
E4: Login
E5: Personal Information
D7: Training Program
D8: Exercise Library (Instructional Videos) | E8: See Exercise Library Through Training Program
E9: See Selection of Exercises
E10: Filter Exercise Selection
E11: Search Through Exercise Selection
E12: Show Exercise Details (Description, Video, Calories, Time, Difficulty)
E13: See Calendar in Training Program
E14: CRUD Workout Calendar
E15: Start Exercise
E16: Exercise Progress (GPS, Machine Input, Duration,Timer Reps, Volume Distance)
E17: Finish Exercise (Summary, Add Description, Images, Etc.)
E18: See Finished Exercise in Calendar
D19: Dashboard
D20: Fitness Data Management (BMI, calories burned, steps taken, active minutes) | E20: Display Current / Next Activity Progress in Dashboard
E21: Display Daily AI Generated Tips
D22: Leaderboard Data Management (Current placement, challenges won) | E22: Display Leaderboard in Dashboard
D23: Workout Data Management (Top exercises) | E23: Display Top Exercises in Dashboard
D27: Rewards and Leaderboard
E28: Achievement Unlocked Notification
E29: View Achievement Details
E30: View Achievements (All, Locked, Unlocked)
E34: CRUD Account Information (Username, Email, Password)
E35: Manage Notification Settings (Workout Reminders, Inactivity Alerts)
E36: Manage Privacy Settings (Profile Visibility)
E37: Logout / Deactivate Account
D38: Personal Fitness Information | E38: CRUD Health Metrics (Age, Height, Current Weight)
E39: CRUD Fitnness Goals (Target Weight, Descired Activity Level)
D40: Avatar Customization | E40: View Current Avatar in Profile
E41: See Avatar in Dashboard
E42: Select / Update User Avatar
D43: Training Program
D44: Exercise Library (Instructional Videos)
D49: Workout Calendar Scheduler
D53: Workout Tracker and Timer
B55: Objective 1: Implement personalized goal-setting and progress visualization through an interactive cardio activity dashboard to enhance user motivation and engagement. | C55: Implementation of Progress Tracking Implementation of User Customization
D56: AI-Generated Adaptive Workout Plan and Recommendations | E56: Generate Adaptive Workout
E57: Display Recommendations After Workout
D58: Progress Tracking
D59: Workout Logs / Activity Reports(Daily, weekly, monthly progress report) | E59: Progress Report Daily, Weekly, Monthly)
E60: Track Fitness Goal (Step Count, Exercise Time, etc)
E61: View Calculated BMI Status (Auto-updated based on weight inputs)
E62: See Fitness Goal Progress Bar in Dashboard
E63: See Activity History From Progress Report
E64: Show Completed Activities in Activity History
E65: Show Details of Completed Activities
D66: Export and Share Feature | E66: Share Progress Report to Feed or Outside Apps
D67: Data Visualization for Performance Trends | E67: Show Graphs and Charts for Progress Reports
E68: Show Graphs and Charts for Individual Activities / Challenges
D69: Rewards and Leaderboard
D70: Achievement Badge System | E70: Achievement Unlocked
E71: View Achievements (All, Locked, Unlocked)
E72: View Achievement Details (Locked, Unlocked)
E73: Show Achievements in Dashboard (Recently Unlocked / Close to Unlocking)
E74: Show Unlocked Achievement in Social Feed
E75: Show Achievements in User Profile (Own Profile, Friends Profile)
E76: CRUD Achievements Displayed
B77: Objective 2: Provide an Adaptive Training System to generate personalized workout activities and user support, tailored to the user's real-time schedule and activity goal. | C77: Implementation of Training Program Implementation of AI Chatbot | E77: Show Achievement That Can be Unlocked From Particular Activity / Challenge
D83: AI Chatbot
D84: Chat Interface | E84: Open / Close AI Chat Window
E85: Input Text Queries (Natural Language Questions)
E86: Display AI Generated Responses
E87: View Chat Session History
E88: Clear Chat History
D89: ML Chatbot Model | E89: Receive Content-Aware Responses (Tailored to user's track data/profile)
E90: Receive NCD-Specific Guidance
E91: Display Safety Warnings / Rejections (If query is medically unsafe or out of scope)
D92: Personalized Assistance | E92: Receive Motivational Responses
D93: Group Fitness Challenge
D94: Friend System | E94: Search for Users
E95: CRUD Friend Requests (Send, Accept, Reject, Cancel)
E96: View Friend List
E97: View Friend Profile (Achievements, Avatar, Basic Stats)
D98: Team Challenges | E98: View Available / Ongoing Group Challenges
E99: Create Join / Leave Group Challenge
E100: View Team Progress (Collective Steps, Distance, etc.)
E101: View Challenge Rules and Duration
B102: Objective 3: Integrate social elements like Community Rankings to increase user engagement and retention through interactive and supportive in-app community. | C102: Implementation of Group Fitness Challenge | E102: See Current Group Fitness Challenge on Dashboard
D103: Community Rankings | E103: View Community Leaderboard
E104: Filter Leaderboard Views (Group Fitness Challenge Only)
D105: Performance Comparison | E105: Stat Comparison with other Group
E106: View Personal Rank in Group Leaderboard
D107: Rewards and Leaderboard
D108: Leaderboard System | E108: View Friend Leaderboard Through Dashboard (Allow Several Categories
E109: View Leaderboard in Group Fitness Challenge

Sheet For Checking
A1: User Customization Phase 1: The Onboarding
A2: Sub-Category / Module | B2: Specific Features / Tasks | C2: Notes / Remarks
A3: Account Management (Settings) | B3: Signup (Email, Password) | C3: Prioritize SignUp over Login Missing "Already Have an Account"
B4: Personal Information | F4: Move "The Basics, Weight Goals..." to First-time Login
A5: Personal Fitness Information | B5: First-Time Setup (The Basics, Weight Goals, Step Goals, Availability Schedule) | C5: Change "The Basics to Personal Information", Move Current weight to Personal Information
B6: CRUD Health Metrics (Age, Height, Current Weight)
B7: CRUD Fitness Goals (Target Weight, Desired Activity Level, Schedule)
B8: Login | F8: Notes / Remarks
B9: CRUD Account Information (Username, Email, Password)
B10: Manage Notification Settings (Workout Reminders, Inactivity Alerts)
B11: Manage Privacy Settings (Profile Visibility)
B12: Logout / Deactivate Account
A13: Avatar Customization | B13: Select / Update User Avatar
B14: View Current Avatar in Profile
B15: See Avatar in Dashboard
A17: Dashboard Phase 2: The Landing
A18: Sub-Category / Module | B18: Specific Features / Tasks | C18: Notes / Remarks
A19: Fitness Data Management | B19: Display Current / Next Activity Progress in Dashboard
B20: Display Daily AI Generated Tips
B21: See Fitness Goal Progress Bar in Dashboard
B22: View Calculated BMI Status (Auto-updated based on weight inputs)
A23: Quick Access & Snapshots | B23: Display Leaderboard in Dashboard
B24: Display Top Exercises in Dashboard
B25: See Current Group Fitness Challenge on Dashboard
B26: Show Achievements in Dashboard (Recently Unlocked / Close to Unlocking)
A28: Fitness Buddy Chatbot Phase 3: The Core Value
A29: Sub-Category / Module | B29: Specific Features / Tasks | C29: Notes / Remarks
A30: Chat Interface | B30: Open / Close AI Chat Window
B31: Input Text Queries (Natural Language Questions)
B32: View Chat Session History
B33: Clear Chat History
A34: AI Responses & Safety | B34: Display AI Generated Responses
B35: Receive Content-Aware Responses (Tailored to user's track data/profile)
B36: Receive NCD-Specific Guidance
B37: Display Safety Warnings / Rejections (If query is medically unsafe/out of scope)
B38: Receive Motivational Responses
A40: Training Program Phase 4: The Action
A41: Sub-Category / Module | B41: Specific Features / Tasks | C41: Notes / Remarks
A42: Exercise Library | B42: See Exercise Library Through Training Program
B43: See Selection of Exercises
B44: Filter Exercise Selection
B45: Search Through Exercise Selection
B46: Show Exercise Details (Description, Video, Calories, Time, Difficulty)
A47: Workout Calendar | B47: See Calendar in Training Program
B48: CRUD Workout Calendar
B49: See Different Workouts For Each Selected Date
B50: See Finished Exercise in Calendar
A51: Workout Execution (Timer) | B51: Start Exercise
B52: Timer (Start, Pause, Finish)
B53: Show Details in Timer (Steps, Distance, Pace, etc)
B54: Exercise Progress (GPS, Machine Input, Duration, Timer Reps, Volume Distance)
B55: Finish Exercise (Summary, Add Description, Images)
A56: AI Adaptation | B56: Ask AI For Updated Workout Calendar
B57: Generate Adaptive Workout
B58: Display Recommendations After Workout
A60: Progress Tracking Phase 5: The Results
A61: Sub-Category / Module | B61: Specific Features / Tasks | C61: Notes / Remarks
A62: Activity History | B62: See Activity History From Progress Report
B63: Show Completed Activities in Activity History
B64: Show Details of Completed Activities
A65: Reports & Visualizations | B65: Progress Report (Daily, Weekly, Monthly)
B66: Track Fitness Goal (Step Count, Exercise Time, etc)
B67: Show Graphs and Charts for Progress Reports
B68: Show Graphs and Charts for Individual Activities / Challenges
B69: Share Progress Report to Feed or Outside Apps
A71: Rewards and Leaderboard Phase 6: The Motivation
A72: Sub-Category / Module | B72: Specific Features / Tasks | C72: Notes / Remarks
A73: Achievements | B73: Achievement Unlocked Notification
B74: View Achievements (All, Locked, Unlocked)
B75: View Achievement Details (Locked, Unlocked)
B76: Show Unlocked Achievement in Social Feed
B77: Show Achievements in User Profile (Own Profile, Friends Profile)
B78: CRUD Achievements Displayed
B79: Show Achievement That Can be Unlocked From Particular Activity / Challenge
A80: Community & Friends | B80: Search for Users
B81: CRUD Friend Requests (Send, Accept, Reject, Cancel)
B82: View Friend List
B83: View Friend Profile (Achievements, Avatar, Basic Stats)
A84: Leaderboards | B84: View Community Leaderboard
B85: View Friend Leaderboard Through Dashboard
B86: View Leaderboard in Group Fitness Challenge
B87: Filter Leaderboard Views (Group Fitness Challenge Only)
B88: Stat Comparison with other Group
B89: View Personal Rank in Group Leaderboard
A91: Group Fitness Challenge
B92: View Available / Ongoing Group Challenges
B93: Create / Join / Leave Group Challenge
B94: View Team Progress (Collective Steps, Distance, etc.)
B95: View Challenge Rules and Duration

Sheet Test2
A1: Problem Statement | B1: Objectives | C1: Scopes | D1: Features | E1: Remarks
A2: How can a mobile health application be designed to provide a platform for Filipino non-gym-goers to overcome the specific motivational barriers, such as lack of time, guidance, and training plan, that prevent them from adhering to a consistent cardiovascular exercise routine? | B2: Main Objective: Design and develop an adaptive, AI-driven mobile platform for Filipino non-gym-goers to overcome motivational barriers and deliver personalized cardio training. | C2: Implementation of Personalized Goal-Setting Structure for planning and monitoring fitness routines aligned with WHO guidelines. | D2: DASHBOARD (MODULE)
D3: - Performance Overview
D4: - Dynamic Visualizations (charts, progress indicators)
D5: - Health "Bits and Tips" Section.
D6: REWARDS & LEADERBOARD (MODULE)
D7: - Achievement Badges
D8: - Points/Ranking System
D9: - Leaderboard Display.
B21: Objective 1: Implement personalized goal-setting and progress visualization through an interactive dashboard. | C21: Implementation of Progress Tracking Analyzing user metrics (like BMI) to generate impactful, accurate progress visualizations. | D21: PROGRESS TRACKING (MODULE)
D22: - Daily, Weekly, Monthly Trend Charts
D23: - Statistical Summaries (Calories, Active Time)
D24: - Goal Attainment Monitor.
B30: Objective 2: Provide an Adaptive Training System to generate personalized workout activities tailored to real-time schedules. | C30: Deployment of Machine Learning Algorithm A fully adaptive plan that adjusts intensity and duration based on fatigue and performance history. | D30: TRAINING PROGRAM (MODULE)
D31: - AI-Generated Adaptive Plans
D32: - Exercise Library (Multimedia)
D33: - Workout Timer & Session Tracker
B56: Objective 3: Provide real-time, context-based hints and guidance via an AI companion. | C56: Implementation of AI-Enabled Companion Powered by a curated knowledge base to deliver instant feedback and training advice. | D56: FITNESS AI CHATBOT (MODULE)
D57: - Intelligent Conversational Assistant
D58: - AI Recommendation Engine
D59: - Adaptive Reminders.
B64: Objective 4: Integrate social elements to increase engagement and retention through a supportive community. | C64: Implementation of Social Ecosystem Recreating gym dynamics via localized peer connections and collaborative challenges. | D64: GROUP FITNESS (MODULE)
D65: - Friend System & Performance Comparison
D66: - Community Rankings
D67: - Team Challenges.

Sheet Try (to Edit)
B1: Objectives | C1: Scopes | D1: Features | E1: Features | F1: Remarks
A2: How can a mobile health application be designed to provide a platform for Filipino non-gym-goers to overcome the specific motivational barriers, such as lack of time, guidance, and training plan, that prevent them from adhering to a consistent cardiovascular exercise routine? | B2: Main Objective: The primary objective of this study is to design and develop an adaptive, AI-driven mobile platform for Filipino non-gym-goers, which leverages gamified engagement to overcome specific motivational barriers (lack of time, guidance, and planning) and deliver personalized cardiovascular training to promote consistent adherence and mitigate NCD risks. | C2: Implementation of Dashboard Implementation of Rewards and Leaderboard Implementation of User Customization | D2: User Customization
D3: Account Management (Settings) | E3: Signup (Email, Password, The Basics, Weight Goals, Step Goals, Availability Schedule, Final Review) | F3: Get Started
E4: Login | F4: Signup
E5: Personal Information | F5: Login
E6: Tutorial | F6: CRUD Information
E7: CRUD Account Information (Username, Email, Password) | F7: Customize Avatar
E8: Manage Notification Settings (Workout Reminders, Inactivity Alerts) | F8: Home/Dashboard
E9: Manage Privacy Settings (Profile Visibility) | F9: Training
E10: Logout / Deactivate Account | F10: Calendar
D11: Personal Fitness Information | E11: CRUD Health Metrics (Age, Height, Current Weight) | F11: Generate AI Plan | G11: --
E12: CRUD Fitnness Goals (Target Weight, Descired Activity Level) | F12: Exercise | G12: Instructions (Video)
D13: Avatar Customization | E13: View Current Avatar in Profile | F13: Finish Exercise | G13: Specify
F14: Progress Tracking
F15: Home/Dashboard
F16: Current Exercise
E17: See Avatar in Dashboard | F17: Chart
E18: Select / Update User Avatar | F18: Metrics
D19: Training Program | F19: Chatbot
D20: Exercise Library (Instructional Videos) | E20: See Exercise Library Through Training Program
E21: See Selection of Exercises | F21: Home/Dashboard | G21: Friends Leaderboard
E22: Filter Exercise Selection | F22: Bits n Tips | G22: Achievements
E23: Search Through Exercise Selection | F23: Profile
E24: Show Exercise Details (Description, Video, Calories, Time, Difficulty)
D25: Workout Calendar Scheduler | E25: See Calendar in Training Program | F25: Edit Profile
E26: See Different Workouts For Each Selected Date | F26: Social
E27: CRUD Workout Calendar | F27: Group Challenge
E28: Ask AI For Updated Workout Calendar
D29: Workout Tracker and Timer | E29: See in Exercises
E30: Timer (Start, Pause, Finish)
B31: Objective 1: Implement personalized goal-setting and progress visualization through an interactive cardio activity dashboard to enhance user motivation and engagement. | C31: Implementation of Progress Tracking Implementation of User Customization | E31: Show Details in Timer (Steps, Distance, Pace, etc)
D32: AI-Generated Adaptive Workout Plan and Recommendations | E32: Generate Adaptive Workout
E33: Display Recommendations After Workout
D34: Progress Tracking
D35: Workout Logs / Activity Reports(Daily, weekly, monthly progress report) | E35: Progress Report Daily, Weekly, Monthly)
E36: Track Fitness Goal (Step Count, Exercise Time, etc)
E37: View Calculated BMI Status (Auto-updated based on weight inputs)
E38: See Fitness Goal Progress Bar in Dashboard
E39: See Activity History From Progress Report
E40: Show Completed Activities in Activity History
E41: Show Details of Completed Activities
D42: Export and Share Feature | E42: Share Progress Report to Feed or Outside Apps
D43: Data Visualization for Performance Trends | E43: Show Graphs and Charts for Progress Reports
E44: Show Graphs and Charts for Individual Activities / Challenges
D45: Rewards and Leaderboard
D46: Achievement Badge System | E46: Achievement Unlocked
E47: View Achievements (All, Locked, Unlocked)
E48: View Achievement Details (Locked, Unlocked)
E49: Show Achievements in Dashboard (Recently Unlocked / Close to Unlocking)
E50: Show Unlocked Achievement in Social Feed
E51: Show Achievements in User Profile (Own Profile, Friends Profile)
E52: CRUD Achievements Displayed
B53: Objective 2: Provide an Adaptive Training System to generate personalized workout activities and user support, tailored to the user's real-time schedule and activity goal. | C53: Implementation of Training Program Implementation of AI Chatbot | E53: Show Achievement That Can be Unlocked From Particular Activity / Challenge
D54: Dashboard
D55: Fitness Data Management (BMI, calories burned, steps taken, active minutes) | E55: Display Current / Next Activity Progress in Dashboard
E56: Display Daily AI Generated Tips
D57: Leaderboard Data Management (Current placement, challenges won) | E57: Display Leaderboard in Dashboard
D58: Workout Data Management (Top exercises) | E58: Display Top Exercises in Dashboard
D59: AI Chatbot
D60: Chat Interface | E60: Open / Close AI Chat Window
E61: Input Text Queries (Natural Language Questions)
E62: Display AI Generated Responses
E63: View Chat Session History
E64: Clear Chat History
D65: ML Chatbot Model | E65: Receive Content-Aware Responses (Tailored to user's track data/profile)
E66: Receive NCD-Specific Guidance
E67: Display Safety Warnings / Rejections (If query is medically unsafe or out of scope)
D68: Personalized Assistance | E68: Receive Motivational Responses
D69: Group Fitness Challenge
D70: Friend System | E70: Search for Users
E71: CRUD Friend Requests (Send, Accept, Reject, Cancel)
E72: View Friend List
E73: View Friend Profile (Achievements, Avatar, Basic Stats)
D74: Team Challenges | E74: View Available / Ongoing Group Challenges
E75: Create Join / Leave Group Challenge
E76: View Team Progress (Collective Steps, Distance, etc.)
E77: View Challenge Rules and Duration
B78: Objective 3: Integrate social elements like Community Rankings to increase user engagement and retention through interactive and supportive in-app community. | C78: Implementation of Group Fitness Challenge | E78: See Current Group Fitness Challenge on Dashboard
D79: Community Rankings | E79: View Community Leaderboard
E80: Filter Leaderboard Views (Group Fitness Challenge Only)
D81: Performance Comparison | E81: Stat Comparison with other Group
E82: View Personal Rank in Group Leaderboard
D83: Rewards and Leaderboard
D84: Leaderboard System | E84: View Friend Leaderboard Through Dashboard (Allow Several Categories
E85: View Leaderboard in Group Fitness Challenge

Sheet Try
A1: Problem Statement | B1: Objectives | C1: Scopes | D1: Features | E1: Features | F1: Remarks
A2: How can a mobile health application be designed to provide a platform for Filipino non-gym-goers to overcome the specific motivational barriers, such as lack of time, guidance, and training plan, that prevent them from adhering to a consistent cardiovascular exercise routine? | B2: Main Objective: The primary objective of this study is to design and develop an adaptive, AI-driven mobile platform for Filipino non-gym-goers, which leverages gamified engagement to overcome specific motivational barriers (lack of time, guidance, and planning) and deliver personalized cardiovascular training to promote consistent adherence and mitigate NCD risks. | C2: Implementation of Dashboard Implementation of Rewards and Leaderboard Implementation of User Customization | D2: User Customization
D3: Account Management (Settings) | E3: Signup (Email, Password, The Basics, Weight Goals, Step Goals, Availability Schedule, Final Review) | F3: Move The Basics, Weight Goals, Step Goals, Availability Schedule, Final Review to First time Login
E4: Login
E5: Personal Information
E6: Tutorial | F6: User Customization
E7: CRUD Account Information (Username, Email, Password) | F7: - Account Management
E8: Manage Notification Settings (Workout Reminders, Inactivity Alerts) | F8: -- Signup
E9: Manage Privacy Settings (Profile Visibility) | F9: -- Login
E10: Logout / Deactivate Account | F10: -- Personal Information
D11: Personal Fitness Information | E11: CRUD Health Metrics (Age, Height, Current Weight) | F11: -- Tutorial
E12: CRUD Fitnness Goals (Target Weight, Descired Activity Level) | F12: -- CRUD Acct Info
D13: Avatar Customization | E13: View Current Avatar in Profile | F13: - Personal Fitness Infor
E14: See Avatar in Dashboard | F14: -- Health Metrics
E15: Select / Update User Avatar | F15: -- Fitness Goals
D16: Training Program
D17: Exercise Library (Instructional Videos) | E17: See Exercise Library Through Training Program
E18: See Selection of Exercises
E19: Filter Exercise Selection
E20: Search Through Exercise Selection
E21: Show Exercise Details (Description, Video, Calories, Time, Difficulty)
D22: Workout Calendar Scheduler | E22: See Calendar in Training Program
E23: See Different Workouts For Each Selected Date
E24: CRUD Workout Calendar
E25: Ask AI For Updated Workout Calendar
D26: Workout Tracker and Timer | E26: See in Exercises
E27: Timer (Start, Pause, Finish)
B28: Objective 1: Implement personalized goal-setting and progress visualization through an interactive cardio activity dashboard to enhance user motivation and engagement. | C28: Implementation of Progress Tracking Implementation of User Customization | E28: Show Details in Timer (Steps, Distance, Pace, etc)
D29: AI-Generated Adaptive Workout Plan and Recommendations | E29: Generate Adaptive Workout
E30: Display Recommendations After Workout
D31: Progress Tracking
D32: Workout Logs / Activity Reports(Daily, weekly, monthly progress report) | E32: Progress Report Daily, Weekly, Monthly)
E33: Track Fitness Goal (Step Count, Exercise Time, etc)
E34: View Calculated BMI Status (Auto-updated based on weight inputs)
E35: See Fitness Goal Progress Bar in Dashboard
E36: See Activity History From Progress Report
E37: Show Completed Activities in Activity History
E38: Show Details of Completed Activities
D39: Export and Share Feature | E39: Share Progress Report to Feed or Outside Apps
D40: Data Visualization for Performance Trends | E40: Show Graphs and Charts for Progress Reports
E41: Show Graphs and Charts for Individual Activities / Challenges
D42: Rewards and Leaderboard
D43: Achievement Badge System | E43: Achievement Unlocked
E44: View Achievements (All, Locked, Unlocked)
E45: View Achievement Details (Locked, Unlocked)
E46: Show Achievements in Dashboard (Recently Unlocked / Close to Unlocking)
E47: Show Unlocked Achievement in Social Feed
E48: Show Achievements in User Profile (Own Profile, Friends Profile)
E49: CRUD Achievements Displayed
B50: Objective 2: Provide an Adaptive Training System to generate personalized workout activities and user support, tailored to the user's real-time schedule and activity goal. | C50: Implementation of Training Program Implementation of AI Chatbot | E50: Show Achievement That Can be Unlocked From Particular Activity / Challenge
D51: Dashboard
D52: Fitness Data Management (BMI, calories burned, steps taken, active minutes) | E52: Display Current / Next Activity Progress in Dashboard
E53: Display Daily AI Generated Tips
D54: Leaderboard Data Management (Current placement, challenges won) | E54: Display Leaderboard in Dashboard
D55: Workout Data Management (Top exercises) | E55: Display Top Exercises in Dashboard
D56: AI Chatbot
D57: Chat Interface | E57: Open / Close AI Chat Window
E58: Input Text Queries (Natural Language Questions)
E59: Display AI Generated Responses
E60: View Chat Session History
E61: Clear Chat History
D62: ML Chatbot Model | E62: Receive Content-Aware Responses (Tailored to user's track data/profile)
E63: Receive NCD-Specific Guidance
E64: Display Safety Warnings / Rejections (If query is medically unsafe or out of scope)
D65: Personalized Assistance | E65: Receive Motivational Responses
D66: Group Fitness Challenge
D67: Friend System | E67: Search for Users
E68: CRUD Friend Requests (Send, Accept, Reject, Cancel)
E69: View Friend List
E70: View Friend Profile (Achievements, Avatar, Basic Stats)
D71: Team Challenges | E71: View Available / Ongoing Group Challenges
E72: Create Join / Leave Group Challenge
E73: View Team Progress (Collective Steps, Distance, etc.)
E74: View Challenge Rules and Duration
B75: Objective 3: Integrate social elements like Community Rankings to increase user engagement and retention through interactive and supportive in-app community. | C75: Implementation of Group Fitness Challenge | E75: See Current Group Fitness Challenge on Dashboard
D76: Community Rankings | E76: View Community Leaderboard
E77: Filter Leaderboard Views (Group Fitness Challenge Only)
D78: Performance Comparison | E78: Stat Comparison with other Group
E79: View Personal Rank in Group Leaderboard
D80: Rewards and Leaderboard
D81: Leaderboard System | E81: View Friend Leaderboard Through Dashboard (Allow Several Categories
E82: View Leaderboard in Group Fitness Challenge

Sheet Sheet2
A1: Problem Statement | B1: Objectives | C1: Scopes | D1: Features | E1: Remarks
A2: How to utilize a digital game-based learning framework in providing supplemental learning tools for reading comprehension that are adaptive and engaging for Filipino learners?” | B2: Main Objective: Support the improvement of students reading comprehension skills and overall literacy through developing an innovative and accessible tool that combines educational content with game-based mechanics and storytelling presented in a visual novel-style format. | C2: Implementation of Web Dashboard - Learner Overview - Grade-Level Analytics - Viewable Graphs and Tables - Downloadable Reports Implementation of Story Mode - Unlockable Badges Implementation of Challenge Mode - Performance Summary - Instant Feedback System Implementation of Tutorial Mode - Interactive Application Walkthrough | D2: Dashboard (MODULE)
D3: - Story Progress of Class and Individual
D4: - Summary of Challenge Attempts (Scoring)
D5: Admin Reports (MODULE)
D6: - Downloadable Report of Dashbaord (PDF)
D7: GAME TUTORIAL (MODULE)
D8: Game Instruction
D9: - Demonstrate How-to-Play (Text Extract)
D10: - Demonstrate How-to-Play (Two Truths)
D11: - Demonstrate How-to-Play (Statement Scrutinize)
D12: ACHIEVEMENTS AND LEADERBOARD (MODULE)
D13: Display Leaderboard
D14: - Top 10 Scores for each game modes
... D20: - Display Badge Image & Details
B21: Objective 1: Integrates narrative-driven storytelling with interactive reading comprehension activities for Filipino students through a visual novel-style format.​ | C21: Implementation of a Story-Mode - Story-Based Reading Gameplay - Multiple Story Levels - Embedded Gameplay Loop | D21: STORYBOARD (MODULE)
D22: Selection of Story Gamemode
D23: Selection of Worlds (Story)
D24: Selection of Levels
D25: Narration (Text-To-Speech, Navigation of Dialogue)
D26: --
D27: Player Choices & Branching Logic
D28: Proceed to Activity
D29: Proceed to Story Level (Lock)
B30: Objective 2: Implement interactive comprehension tasks where learners engage through various literary passages and excerpts such as poems, novels, and inspirational quotes to foster active reading and deeper understanding. | C30: Implementation of Challenge Mode - Multiple Gamemodes (Text Extraction, Two Truths and a Lie, Statement Scrutinize) | D30: CHALLENGE MODE (MODULE)
D31: Selection of Challenge Gamemode
D32: Selection of Activity Type (Text Extraction, Two Truths and a Lie, Statement Scrutinize)
D33: Selection of Theme
D34: Text Extraction
D35: - 5 Questions
D36: - Drag and Drop
D37: - Pop Up Feedback After Every Question
D38: - AI Assistant (User Message, Chatbot Response)
D39: - Real Time Score Display
D41: Two Truths and a Lie
D42: - 5 Questions
D43: - 3 Choices, 2 are incorrect, 1 is correct
... D55: - Real Time Score Display
B56: Objective 3: Provide practice sets by utilizing an AI system to automatically generate reading prompts with relevant reading comprehension questions. | C56: Implementation of Challenge Mode - LLM-Generated Reading Tasks | D56: AI ASSISTANT (MODULE)
D57: Generation of Reading Comprehension Task
D58: - Filter of Correct Format
D59: --- Text Extract: text_passage;question;answer
D60: --- Two Truths: text_passage;statement1|statement2|statement3;num_answer
D61: --- Statement Scrutinize: text_passage;statement1|statement2|statement3;num_answer|evidence
B64: Objective 4: Provide real-time, context-based hints and guidance to support learners in answering comprehension questions effectively by developing an AI companion. | C64: Implementation of Challenge Mode - AI-Enabled Companion | D64: AI ASSISTANT (MODULE)
D65: User Messaging Function
D66: Chatbot Response Function

Sheet NULL
A1: One pressing challenge is the limited opportunity for Filipino students to engage in reading comprehension practice beyond the classroom. As noted by Idulog (2023), Without accessible and engaging platforms to reinforce reading habits at home or in informal environments, students are unable to develop consistent reading routines or deepen their understanding through independent learning. This disconnect between in-school instruction and at-home reinforcement hinders the development of strong reading habits and foundational skills.
A2: Integrates narrative-driven storytelling with interactive reading comprehension activities for Filipino students through a visual novel-style format.​
A3: The application will focus on enhancing English reading comprehension through interactive, story-based gameplay. By embedding reading tasks into a visual novel and game format, the system will simulate immersive, real-life reading experiences in English that promote vocabulary acquisition, context interpretation, and inferencing. Additionally, these narratives drawing from English-translated Filipino storybooks, folktales, and familiar community settings, will naturally encourage cultural relevance and connection. This will enable learners to connect new English concepts to their existing cultural schema. This platform is intended to support second-language acquisition by increasing student motivation and engagement by combining entertainment with literacy learning that feel meaningful and relatable to Filipino students.
B4: STORYBOARD (MODULE)
A10: Moreover, traditional classroom materials, such as textbooks and worksheets, are often static, lacking the interactivity needed to encourage active reading. (DepEd, 2023; Dludla et al., 2024). This approach reduces students’ ability to engage critically with texts, especially when it comes to poetry and literature that require interpretation and deeper comprehension. The absence of multimedia tools, gamified learning elements, and scaffolded reading environments contributes to a passive reading culture, making it difficult for students to relate to or internalize complex texts. (Dludla, T., et al., 2024)
A11: Implement interactive comprehension tasks where learners engage through various literary passages and excerpts such as poems, novels, and inspirational quotes to foster active reading and deeper understanding.
A12: The application will incorporate a wide range of English-language texts, including literary excerpts, short poems, and thought-provoking quotations, tailored to the comprehension levels and grade levels of Philippine students. Additionally, these reading passages will be followed by structured tasks via drag and drop reading comprehension questions designed to assess literal, inferential, and critical understanding. This allows support of development in the core English reading skills such as skimming, scanning, context clue analysis, and text interpretation.
B13: PRACTICE MODE (MODULE)
A17: Furthermore, students often run out of meaningful practice materials, especially outside school hours, as current educational apps and modules usually offer a fixed set of questions, limiting continuous improvement. This limitation in available content leads to repetitive learning experiences, diminishing motivation and failing to address diverse learner needs across reading levels and interests. (PIDS, 2023)
A18: Provide practice sets by utilizing an AI system to automatically generate reading prompts with relevant reading comprehension questions.
A19: This mode offers continuous practice in English reading through AI-generated texts and comprehension questions. The AI-enabled system will curate reading materials across various genres and pre-set difficulty levels, ensuring learners have access to personalized, level-appropriate English content. By supplying limitless practice opportunities, this supports mastery through repetition, encourages independent learning, and helps address the scarcity of reading materials in traditional classrooms.
B20: AI ASSISTANT (MODULE)
C21: Generation of Reading Comprehension Task
A25: In addition, as students encounter difficulties in understanding complex prompts on their own, they do not have immediate access to a teacher or tutor outside of class to ask for assistance or get feedback on their work. As a result, students become discouraged when they cannot clarify confusing instructions or verify their answers, which ultimately slows down learning progress and affects confidence in comprehension tasks (Fitria, T.N., 2021).
A26: Provide real-time, context-based hints and guidance to support learners in answering comprehension questions effectively by developing an AI companion.
A27: The AI-enabled companion will act as a reinforcement for an intelligent support system that offers hints, definitions, and guidance in English to support learners as users answer comprehension questions. By providing timely, contextual feedback in English, the AI-enabled companion will help students better understand text structure, unfamiliar vocabulary, and nuanced meanings. The AI-enabled companion guidance is aimed at developing learner confidence, improving accuracy, and building independent reading strategies in English.
B28: AI ASSISTANT (MODULE)
